{
  "name": "MULTI Research Group",
  "fullName": "Machine learning, Uncertainty visualization, Large-scale visualization, Tensor visualization, and Inverse problem",
  "institution": "Scientific Computing and Imaging (SCI) Institute",
  "university": "University of Utah",
  "introduction": "The MULTI research group focuses on advancing the fields of machine learning, uncertainty visualization, large-scale visualization, tensor visualization, and inverse problems. Our interdisciplinary team develops novel computational methods and visualization techniques to address complex scientific challenges."
}
